{
  "id": "harunur-rashid-khan",
  "name": "Harunur Rashid Khan",
  "title": "Adjunct Faculty",
  "department": "Department of English & Humanities (DEH)",
  "school": "",
  "profile_url": "https://ulab.edu.bd/faculty/harunur-rashid-khan",
  "photo_url": "https://ulab.edu.bd/sites/default/files/styles/faculty_avatar/public/images/faculty/harunur-rashid-khan-300.jpg?itok=ymMWtWg_",
  "bio_raw": "Harunur Rashid Khan is currently working as Visiting Faculty (Associate Professor) at the University of Liberal Arts Bangladesh. Previously, he taught at Brac University as adjunct faculty for its MA TESOL program at BIL and also at the English Department of Southeast University and East West University for more than 20 years where he was the head of the department in both places. He studied English Literature, TESOL and Applied Linguistics in Bangladesh, Australia and New Zealand. He received intensive training in ELT materials design in England as well. His teaching usually covers linguistics and various ELT courses. He supervised many MA dissertations on various topics in ELT. He has carried out small- and large-scale projects funded by BRAC, ADB, UNICEF, NETz Bangladesh and British Council. He has published professional articles in peer-reviewed journals at home and abroad and has co-authored textbooks. Mr Khan is former president of BELTA and member of AsiaTEFL (South Korea), IATEFL (UK) & TESOL (USA).",
  "stated_interests": [
    "ELT Methodology, Language Teacher Identity, Critical Pedagogy, Narratology."
  ],
  "education": [
    {
      "raw": "Education\nMA in Applied Linguistics\n– Victoria University of Wellington\nGraduate Diploma in TESOL\n– University of Canberra\nBachelor in Education\n– National University\nMA and BA in English Literature\n– Jahangirnagar University"
    }
  ],
  "publications_raw": [
    "Books\nBabar Chithi\n– a translation work in Bengali. Papysus Publisher.\nKhan, Harunur Rashid\n.\nGlobalization: Culture Shift or Culture Domination? A chapter in a book.\nIdentity: Local and Global\nby Kar & Baral (eds). pp.88-97 by Pencraft International Delhi, December 2003\nCoauthored with Banerji, K, Barua, M. & Matin, J.\nEnglish Grammar Book for Class VII\n, published by NCTB 2016\nJournal Articles: Aktar, T, Manıruzzaman, M.,\nKhan, H. R.\n& Hasan, M. (2022). TEACHERS’ NARRATIVES FROM INITIAL VIRTUAL CLASSROOMS AND PROFESSIONAL DEVELOPMENT DURING THE COVID-19 PANDEMIC IN DEVELOPING BANGLADESH.\nTurkish Online Journal of Distance Education\n, 23 (3), 230-245. Retrieved from https://dergipark.org.tr/en/pub/tojde/issue/70682/1137293\nKhan, Harunur Rashid and Rahaman, Adilur. (2019)\nGlocal Subjectivity, Material Design, and English Language Textbook in Bangladesh: A Sociological Analysis\n.\n3L Journal\n, Malaysia\nKhan, Harunur Rashid and Rahaman, Adilur. ‘National Language Policies and Resistance: An Economic Perspective’,\nEnglish Department Journal of Southeast University\n, Vol. 2, Issue 1, December 2017\nKhan, Harunur Rashid and Rahaman Adilur. ‘Theorizing Motivation for EFL Writing Classrooms at Tertiary Level: A Post Colonial Intervention.\nBELTA Journal,\nVol. 1, Issue 1, 2017\nKhan, Harunur Rashid and Rahaman Adilur. Do English Teachers Qualities Affect Student Performance? An explanatory study from Bangladesh.\nMalaysian Journal of ELT Research\n, Vol. 13, Issue, 2016\nKhan, Harunur Rashid and Rahaman Adilur. ‘Attributes of English Language Teachers at a Private University in Bangladesh: A Descriptive Study’,\nSoutheast University Journal of English Department\n, Vol. 1."
  ],
  "extracted_keywords": [
    {
      "term": "English Language Teacher Education",
      "canonical": "English Language Teacher Education",
      "weight": 0.4,
      "source": "pubs",
      "verified": false
    },
    {
      "term": "Teacher Identity",
      "canonical": "Teacher Identity",
      "weight": 0.3,
      "source": "bio+pubs",
      "verified": false
    },
    {
      "term": "English Language Teaching Methodology",
      "canonical": "English Language Teacher Education",
      "weight": 0.4,
      "source": "bio+pubs",
      "verified": false
    },
    {
      "term": "Narratology",
      "canonical": "Narratology",
      "weight": 0.2,
      "source": "bio+interests",
      "verified": false
    },
    {
      "term": "Critical Pedagogy",
      "canonical": "Pedagogy",
      "weight": 0.3,
      "source": "bio+interests",
      "verified": false
    },
    {
      "term": "Language Teacher Education",
      "canonical": "English Language Teacher Education",
      "weight": 0.4,
      "source": "pubs",
      "verified": false
    }
  ],
  "embedding": [
    0.03563880920410156,
    0.0317821241915226,
    -0.035771701484918594,
    0.026924381032586098,
    0.0373358391225338,
    0.06411024928092957,
    0.019514840096235275,
    0.008895698934793472,
    -0.021897349506616592,
    -0.02243085578083992,
    0.00453000096604228,
    -0.030846403911709785,
    0.0631091296672821,
    -0.03744921833276749,
    0.06633024662733078,
    0.02251202054321766,
    -0.025417907163500786,
    -0.03498884662985802,
    -0.00265403650701046,
    -0.16241054236888885,
    -0.04817255213856697,
    0.06056811660528183,
    0.040533069521188736,
    -0.015788929536938667,
    -0.03945967182517052,
    -0.10995490103960037,
    0.045805685222148895,
    -0.15853191912174225,
    -0.008018321357667446,
    -0.09213035553693771,
    0.013550171628594398,
    0.004337893333286047,
    -0.002940000966191292,
    0.015530040487647057,
    0.051061879843473434,
    0.09706687182188034,
    -0.054866973310709,
    -0.00016430973482783884,
    -0.0441916398704052,
    -0.027629900723695755,
    0.006116779055446386,
    -0.034574657678604126,
    -0.020601660013198853,
    0.005925648380070925,
    0.022215262055397034,
    -0.08324871212244034,
    0.055379871279001236,
    -0.030352063477039337,
    -0.12171689420938492,
    0.06402510404586792,
    -0.031095344573259354,
    -0.030160142108798027,
    0.02777622826397419,
    -0.05355983227491379,
    -0.05284806713461876,
    0.011882377788424492,
    0.01835610531270504,
    0.12573501467704773,
    0.019559334963560104,
    -0.04965731501579285,
    -0.03596882149577141,
    0.04766736552119255,
    -0.06479431688785553,
    -0.022080060094594955,
    -0.011584199033677578,
    -0.05939787998795509,
    0.03078651987016201,
    0.08548741042613983,
    0.03894772380590439,
    0.01762641780078411,
    -0.01806648075580597,
    -0.009820963256061077,
    0.008579511195421219,
    0.05862797796726227,
    0.046602774411439896,
    -0.0807257890701294,
    0.02322383224964142,
    0.02543732337653637,
    0.02822183445096016,
    0.015175843611359596,
    0.026242801919579506,
    0.015940679237246513,
    0.07822749763727188,
    -0.060737885534763336,
    -0.017186500132083893,
    -0.028284404426813126,
    -0.013698085211217403,
    -0.0038581625558435917,
    -0.012107795104384422,
    -0.033636100590229034,
    0.08381012082099915,
    -0.02503942884504795,
    -0.005976492073386908,
    0.03859558701515198,
    0.009950394742190838,
    -0.02414458431303501,
    -0.046969786286354065,
    0.034507159143686295,
    -0.029517168179154396,
    0.053042490035295486,
    -0.009901507757604122,
    0.03033827431499958,
    -0.022571200504899025,
    0.019867675378918648,
    -0.06855835020542145,
    -0.03657493740320206,
    -0.030994368717074394,
    -0.012529827654361725,
    0.019187016412615776,
    -0.024092061445116997,
    -0.02166595496237278,
    0.030713118612766266,
    -0.03772219642996788,
    0.014325390569865704,
    0.07292070239782333,
    0.03781462460756302,
    -0.00832417793571949,
    -0.017926443368196487,
    -0.023384571075439453,
    -0.03541162237524986,
    0.013790508732199669,
    0.06257665157318115,
    0.06653869152069092,
    -0.06420304626226425,
    0.03359190374612808,
    -0.13017691671848297,
    -0.05401822552084923,
    7.349998833707132e-33,
    0.07520899176597595,
    0.06068173423409462,
    0.05825721099972725,
    0.015300869941711426,
    -0.13115514814853668,
    -0.039552316069602966,
    0.03139500319957733,
    0.021687760949134827,
    -0.016526514664292336,
    -0.046798545867204666,
    0.10200569033622742,
    0.014408388175070286,
    0.05147789791226387,
    0.034475021064281464,
    -0.04976702108979225,
    -0.016605963930487633,
    0.0010662676068022847,
    0.03845074400305748,
    -0.06648261845111847,
    0.02715921960771084,
    -0.06431605666875839,
    0.03955665975809097,
    0.04799331724643707,
    -0.06361749768257141,
    -0.008975855074822903,
    0.029558196663856506,
    0.10044854879379272,
    -0.037316009402275085,
    0.11396896094083786,
    0.051420990377664566,
    -0.029211806133389473,
    -0.026168758049607277,
    -0.060514673590660095,
    0.017520945519208908,
    -0.037160396575927734,
    -0.04074180871248245,
    -0.07667642831802368,
    -0.041394222527742386,
    0.014606769196689129,
    -0.06088580563664436,
    0.0021503984462469816,
    0.05828345566987991,
    0.09799657016992569,
    -0.059910550713539124,
    -0.024373222142457962,
    -0.009518355131149292,
    0.10822814702987671,
    0.030414115637540817,
    0.059377070516347885,
    0.005381646100431681,
    -0.06330246478319168,
    -0.06986641883850098,
    -0.029821721836924553,
    -0.01815842278301716,
    0.13336557149887085,
    -0.014526608400046825,
    0.012080200016498566,
    0.03801588714122772,
    0.03527132421731949,
    -0.015920545905828476,
    0.036771368235349655,
    -0.055182844400405884,
    -0.05382511392235756,
    0.08553043752908707,
    0.0036241908092051744,
    -0.04536139592528343,
    -0.12480330467224121,
    -0.03059983067214489,
    0.06323103606700897,
    -0.04165949672460556,
    -0.02229674905538559,
    -0.016420187428593636,
    0.025509146973490715,
    0.041305817663669586,
    -0.0594535768032074,
    -0.03828359767794609,
    0.023441435769200325,
    0.02148916758596897,
    -0.0385776124894619,
    0.06907205283641815,
    -0.032989900559186935,
    0.007521042134612799,
    0.1008465588092804,
    -0.12932610511779785,
    -0.06603647768497467,
    -0.011296954937279224,
    0.024914419278502464,
    -0.04143457114696503,
    0.10212802141904831,
    0.039521168917417526,
    -0.003969924058765173,
    -0.055992987006902695,
    -0.00861642137169838,
    0.043842196464538574,
    -0.00019025761866942048,
    -7.743902582563865e-33,
    -0.012317211367189884,
    0.03296293318271637,
    -0.04296157881617546,
    0.0013685059966519475,
    0.016191618517041206,
    0.014010285027325153,
    0.10368865728378296,
    0.0866345763206482,
    -0.010197102092206478,
    -0.05947096273303032,
    0.029506664723157883,
    -0.009486987255513668,
    0.014282885938882828,
    0.001225166255608201,
    0.025112269446253777,
    -0.014279229566454887,
    0.06168701872229576,
    -0.05195297300815582,
    0.006398002617061138,
    0.04154983535408974,
    -0.06841668486595154,
    -0.010567808523774147,
    -0.0730065181851387,
    -0.027872364968061447,
    0.00024798334925435483,
    -0.004489458166062832,
    -0.020974114537239075,
    -0.07701804488897324,
    -0.07876777648925781,
    0.052048053592443466,
    -0.018680665642023087,
    -0.06017187982797623,
    -0.051174212247133255,
    0.09873036295175552,
    -0.10888876020908356,
    -0.011079706251621246,
    -0.012862305156886578,
    0.00996900163590908,
    -0.04982380196452141,
    0.08552075922489166,
    0.02979448437690735,
    -0.0005732563440687954,
    0.020457157865166664,
    -0.11225287616252899,
    0.00848586205393076,
    0.037058405578136444,
    -0.04736781865358353,
    -0.010877485387027264,
    0.0055566937662661076,
    -0.040042128413915634,
    0.05965329334139824,
    0.02085971087217331,
    0.043014634400606155,
    -0.11574618518352509,
    0.04982803016901016,
    -0.0021430030465126038,
    0.02783305197954178,
    -0.0664898082613945,
    -0.00562983239069581,
    -0.06654391437768936,
    0.024750124663114548,
    0.06364596635103226,
    0.06250517070293427,
    -0.01315124612301588,
    -0.047395724803209305,
    -0.07264899462461472,
    -0.010518142953515053,
    0.046818219125270844,
    0.004598559811711311,
    -0.0427280031144619,
    0.021798813715577126,
    0.039969027042388916,
    -0.015101145952939987,
    -0.04190827161073685,
    -0.012310219928622246,
    0.045907583087682724,
    -0.03301992267370224,
    0.005749571602791548,
    -0.04371638223528862,
    -0.013380571268498898,
    -0.004408249165862799,
    -0.010421131737530231,
    -0.04698945954442024,
    -0.04624227061867714,
    0.045529793947935104,
    0.038361504673957825,
    -0.005630777217447758,
    -0.05913081765174866,
    0.14091306924819946,
    -0.0030332335736602545,
    -0.027807457372546196,
    0.02162199281156063,
    0.05982855707406998,
    0.07822895795106888,
    0.06621354073286057,
    -5.89824900032454e-8,
    -0.05982204154133797,
    -0.10791777074337006,
    -0.05480993166565895,
    -0.013699602335691452,
    -0.06442482769489288,
    0.023605523630976677,
    -0.026516731828451157,
    -0.008134490810334682,
    -0.03603024780750275,
    0.0666220635175705,
    -0.02480139024555683,
    -0.005822575185447931,
    -0.028810083866119385,
    -0.06574305891990662,
    0.007923278957605362,
    -0.04033157229423523,
    0.06447575241327286,
    0.027344124391674995,
    -0.0008980613201856613,
    -0.030842969194054604,
    0.07274770736694336,
    0.03626468405127525,
    0.0012593417195603251,
    0.030982153490185738,
    -0.027470918372273445,
    0.07764694839715958,
    0.030015969648957253,
    -0.002506277523934841,
    0.01091004442423582,
    -0.024727126583456993,
    -0.027026856318116188,
    0.045518260449171066,
    -0.030032984912395477,
    -0.05717245116829872,
    0.031038882210850716,
    0.05935453623533249,
    0.0803787112236023,
    0.005297430325299501,
    0.029984047636389732,
    0.19291605055332184,
    0.009117071516811848,
    0.0426805354654789,
    0.057174600660800934,
    -0.005257683340460062,
    0.03911552205681801,
    -0.02296229638159275,
    -0.05965714901685715,
    -0.02063900977373123,
    0.022125661373138428,
    -0.020196352154016495,
    -0.09549602121114731,
    -0.05232783779501915,
    -0.0013681824784725904,
    -0.03846174478530884,
    0.10843309760093689,
    0.0068888128735125065,
    -0.018891124054789543,
    -0.0737459808588028,
    -0.05651654675602913,
    0.023545589298009872,
    0.06236451864242554,
    -0.06117803230881691,
    0.038390614092350006,
    0.04653209447860718
  ],
  "locked_fields": [],
  "local_image_path": "C:\\Users\\atanu\\Desktop\\ULAB-DomainNetwork\\scraper\\..\\data\\images\\harunur-rashid-khan.jpg",
  "keyword_extractions": {
    "legacy": {
      "keywords": [
        {
          "term": "English Language Textbook",
          "canonical": "ELT materials design",
          "weight": 0.7,
          "source": "bio+pubs",
          "verified": true
        },
        {
          "term": "Critical Pedagogy",
          "canonical": "critical pedagogy",
          "weight": 0.8,
          "source": "bio+inter",
          "verified": true
        },
        {
          "term": "Narratology",
          "canonical": "narrative theory",
          "weight": 0.6,
          "source": "bio+interests",
          "verified": false
        },
        {
          "term": "Language Teacher Identity",
          "canonical": "teacher identity",
          "weight": 0.9,
          "source": "bio+pubs",
          "verified": true
        },
        {
          "term": "ELT Methodology",
          "canonical": "English Language Teaching methods",
          "weight": 0.7,
          "source": "bio+interests",
          "verified": false
        },
        {
          "term": "Globalization: Culture Shift or Culture Domination?",
          "canonical": "globalization and culture shift",
          "weight": 0.8,
          "source": "pubs",
          "verified": true
        },
        {
          "term": "TEACHERS’ NARRATIVES FROM INITIAL VIRTUAL CLASSROOMS AND PROFESSIONAL DEVELOPMENT DURING THE COVID-19 PANDEMIC IN DEVELOPING BANGLADESH",
          "canonical": "teacher narratives and pandemic response",
          "weight": 0.9,
          "source": "pubs",
          "verified": true
        },
        {
          "term": "Glocal Subjectivity, Material Design, and English Language Textbook in Bangladesh: A Sociological Analysis",
          "canonical": "glocal subjectivity and ELT materials design",
          "weight": 0.8,
          "source": "pubs",
          "verified": true
        },
        {
          "term": "National Language Policies and Resistance: An Economic Perspective",
          "canonical": "language policy and resistance",
          "weight": 0.7,
          "source": "pubs",
          "verified": true
        },
        {
          "term": "Motivation for EFL Writing Classrooms at Tertiary Level: A Post Colonial Intervention",
          "canonical": "motivation in EFL writing classrooms",
          "weight": 0.8,
          "source": "pubs",
          "verified": true
        },
        {
          "term": "Do English Teachers Qualities Affect Student Performance? An explanatory study from Bangladesh",
          "canonical": "teacher qualities and student performance",
          "weight": 0.7,
          "source": "pubs",
          "verified": true
        }
      ],
      "extracted_at": null
    },
    "llama3:8b": {
      "keywords": [
        {
          "term": "English Language Teacher Education",
          "canonical": "English Language Teacher Education",
          "weight": 0.4,
          "source": "pubs",
          "verified": false
        },
        {
          "term": "Teacher Identity",
          "canonical": "Teacher Identity",
          "weight": 0.3,
          "source": "bio+pubs",
          "verified": false
        },
        {
          "term": "English Language Teaching Methodology",
          "canonical": "English Language Teaching Methodology",
          "weight": 0.4,
          "source": "bio+pubs",
          "verified": false
        },
        {
          "term": "Narratology",
          "canonical": "Narratology",
          "weight": 0.2,
          "source": "bio+interests",
          "verified": false
        },
        {
          "term": "Critical Pedagogy",
          "canonical": "Critical Pedagogy",
          "weight": 0.3,
          "source": "bio+interests",
          "verified": false
        },
        {
          "term": "Language Teacher Education",
          "canonical": "Language Teacher Education",
          "weight": 0.4,
          "source": "pubs",
          "verified": false
        }
      ],
      "extracted_at": "2026-07-14T03:56:32.291892+00:00"
    }
  },
  "active_extraction_model": "llama3:8b"
}