{
  "id": "muhammad-aminuzzaman",
  "name": "Muhammad Aminuzzaman",
  "title": "Senior Lecturer",
  "department": "School of Social Science",
  "school": "",
  "profile_url": "https://ulab.edu.bd/faculty/muhammad-aminuzzaman",
  "photo_url": "https://ulab.edu.bd/sites/default/files/styles/faculty_avatar/public/images/faculty/Muhammad-Aminuzzaman.jpg?itok=ScV8z4K5",
  "bio_raw": "From 2014- August 2018: Aminuzzaman has 4 years’ experience in teaching in the Department of Film, Television and Digital Media at the Green University of Bangladesh. He also has 10 years’ experience in professional photography and teaching as a part-time faculty at Pathshala, The South Asian Media Institute in Dhaka. He was involved in the production of international documentaries for BBC Earth Report as a researcher, camera and sound person in Bangladesh and India. He Worked in Drik India, Kolkata, India as a photographer from Aug 2004-July 2005.",
  "stated_interests": [
    "Photography",
    "Multimedia Journalism",
    "Film History",
    "Communication and Technology"
  ],
  "education": [
    {
      "raw": "Education\nM.Com\n(Marketing), University of Dhaka\nB.Com\n(Hons.) in Marketing, University of Dhaka"
    }
  ],
  "publications_raw": [
    "Books\nPhoto story “Our world of Water” Oxfam UK, 2008, Author Beatrice Hollyer and Multiple photographers\nISBN: 978-1-84507-973-4\nDate: 10/01/2008\nThe First Element (Book), 2003\nPublisher: National Art Gallery, Kuala Lumpur, Multiple photographers ISBN: 983-9572-64-4\nDate: 02/03/2003\nTourist Attractions of Bangladesh\nPublished by External Publicity Wing Ministry of Foreign Affairs, Government of the People’s Republic of Bangladesh",
    "Journal Articles\nMetric Topology and Visual Perception of Image\nNovember 2018 (Online)\nDecember 2018 (Print)\nDr Mir Mohammad Azad, M N I Chowdhury,\nMuhammad Aminuzzaman\nInternational Journal of New Technology and Research, India\nImpact Factor 3.953 ISSN:2454-4116.\nDate: 05/01/2018",
    "Newspaper & Magazines\nCover page story, Water’s Others Name is Life\nSaudi Aramco World\nJuly/August 2002 USA\nwww.saudiaramco.com\nDate: 08/26/2002",
    "Works\nTraining on Multimedia Journalism Workshop for Rural Journalists\nDrikNEWS and Rural Journalism Network (RVJN)\nDrik Picture Library Ltd\nDate: 02/29/2020"
  ],
  "extracted_keywords": [
    {
      "term": "Metric Topology",
      "canonical": "Metric Topology",
      "weight": 0.7,
      "source": "pubs",
      "verified": true
    },
    {
      "term": "Visual Perception",
      "canonical": "Visual Perception",
      "weight": 0.6,
      "source": "pubs",
      "verified": true
    },
    {
      "term": "Image Processing",
      "canonical": "Image Processing",
      "weight": 0.5,
      "source": "bio+pubs",
      "verified": false
    },
    {
      "term": "Multimedia Journalism",
      "canonical": "Multimedia Journalism",
      "weight": 0.8,
      "source": "bio+pubs",
      "verified": true
    },
    {
      "term": "Rural Journalists",
      "canonical": "Rural Journalists",
      "weight": 0.4,
      "source": "works",
      "verified": false
    },
    {
      "term": "Photography Education",
      "canonical": "Photography Education",
      "weight": 0.3,
      "source": "bio+pubs",
      "verified": false
    },
    {
      "term": "Journalism and Technology",
      "canonical": "Communication and Technology",
      "weight": 0.9,
      "source": "interesets",
      "verified": true
    },
    {
      "term": "Film History",
      "canonical": "Film History",
      "weight": 0.5,
      "source": "bio+pubs",
      "verified": false
    },
    {
      "term": "Digital Media Production",
      "canonical": "Digital Media Production",
      "weight": 0.6,
      "source": "bio+pubs",
      "verified": true
    },
    {
      "term": "Documentary Film Production",
      "canonical": "Documentary Film Production",
      "weight": 0.8,
      "source": "bio+pubs",
      "verified": true
    }
  ],
  "embedding": [
    0.04389146715402603,
    0.02300664782524109,
    -0.09821410477161407,
    -0.011542684398591518,
    0.03247235715389252,
    0.01759348250925541,
    -0.055209800601005554,
    0.05407188460230827,
    -0.045115984976291656,
    0.001329230610281229,
    0.019982675090432167,
    -0.1123337522149086,
    0.06028950586915016,
    0.07116302847862244,
    0.0024575202260166407,
    0.020588945597410202,
    0.0021465213503688574,
    -0.024709779769182205,
    0.035370104014873505,
    -0.0708002969622612,
    -0.031168408691883087,
    0.038418788462877274,
    0.11716846376657486,
    -0.05734854191541672,
    0.007974717766046524,
    0.012303401716053486,
    0.005272489506751299,
    -0.04335609823465347,
    0.0321291945874691,
    -0.06457715481519699,
    0.04927213862538338,
    0.06715107709169388,
    0.012661968357861042,
    -0.01533902995288372,
    0.09746897220611572,
    0.07846282422542572,
    0.032901640981435776,
    0.0005662427865900099,
    -0.07868964970111847,
    -0.06028829142451286,
    0.01307175774127245,
    0.03500274941325188,
    0.011998843401670456,
    -0.08918587863445282,
    0.02688985876739025,
    -0.029330285266041756,
    -0.008713744580745697,
    0.03415745496749878,
    -0.03629804775118828,
    -0.013683539815247059,
    -0.11741811037063599,
    -0.0257459357380867,
    -0.011664171703159809,
    -0.03756174445152283,
    0.048224713653326035,
    -0.02183159813284874,
    0.0035665573086589575,
    0.0060384864918887615,
    -0.010632065124809742,
    -0.03979095444083214,
    0.03543651103973389,
    0.0348551981151104,
    -0.09889096021652222,
    0.04131791740655899,
    0.08229166269302368,
    0.01573200523853302,
    0.0006436315015889704,
    -0.029963096603751183,
    0.028408555313944817,
    -0.07136370241641998,
    -0.01081390492618084,
    -0.018713174387812614,
    -0.004787098616361618,
    0.001747078145854175,
    -0.0872025266289711,
    -0.08431442826986313,
    0.01616712100803852,
    0.01048313733190298,
    -0.04553251713514328,
    -0.022619448602199554,
    0.10639916360378265,
    0.008316035382449627,
    0.06888863444328308,
    -0.046831220388412476,
    -0.0120729710906744,
    -0.04660639539361,
    -0.028125450015068054,
    0.023816484957933426,
    -0.10335628688335419,
    -0.04537901282310486,
    0.02465607039630413,
    -0.07131793349981308,
    -0.03225536644458771,
    0.010539296083152294,
    -0.0366094745695591,
    -0.07944437116384506,
    -0.019964205101132393,
    -0.007286595646291971,
    0.07996388524770737,
    0.0445505827665329,
    0.008093615993857384,
    -0.0773109719157219,
    -0.07644963264465332,
    -0.08346549421548843,
    -0.04256428778171539,
    0.02364039234817028,
    0.07382284104824066,
    0.06733883917331696,
    -0.009919620119035244,
    0.042022984474897385,
    -0.04789675027132034,
    0.03633752837777138,
    -0.11278381198644638,
    0.03269088640809059,
    0.06707804650068283,
    0.02475443109869957,
    -0.014596136286854744,
    0.0015289658913388848,
    -0.011376776732504368,
    -0.060964301228523254,
    0.002052249386906624,
    0.004462979268282652,
    -0.013213968835771084,
    -0.026959877461194992,
    -0.006694739684462547,
    -0.11092903465032578,
    0.037586510181427,
    2.48019499992513e-33,
    0.07309752702713013,
    0.00033499448909424245,
    0.04104066267609596,
    -0.06262180954217911,
    0.02183389849960804,
    0.10576692223548889,
    -0.02068064734339714,
    0.0687544196844101,
    0.0226905420422554,
    -0.07708907127380371,
    0.024550650268793106,
    0.0072877793572843075,
    0.0029405325185507536,
    0.05429449304938316,
    -0.026133211329579353,
    0.03649546951055527,
    -0.06970103830099106,
    0.0198839008808136,
    -0.014920934103429317,
    0.02151404693722725,
    -0.002402205253019929,
    0.004446142818778753,
    0.0655428022146225,
    0.09381872415542603,
    0.029926316812634468,
    0.031113306060433388,
    0.06499680876731873,
    -0.020413098856806755,
    0.06991685926914215,
    0.02553125098347664,
    -0.01898692362010479,
    0.05841609835624695,
    -0.10594695806503296,
    -0.07418264448642731,
    0.0012076860293745995,
    0.005152812227606773,
    -0.045767150819301605,
    -0.03730958700180054,
    -0.00024753116304054856,
    0.036528851836919785,
    0.010236283764243126,
    0.052307430654764175,
    -0.07544397562742233,
    -0.033167604357004166,
    -0.014822308905422688,
    0.14001047611236572,
    0.09982750564813614,
    0.07563446462154388,
    -0.0008905466529540718,
    0.01799965463578701,
    -0.055679209530353546,
    -0.043536070734262466,
    -0.07241254299879074,
    -0.0829327329993248,
    0.03183634951710701,
    0.03967360779643059,
    0.03120691329240799,
    -0.05519085004925728,
    0.04752226546406746,
    -0.08382228016853333,
    0.06612391024827957,
    0.005959747359156609,
    -0.02945072203874588,
    0.0003468362265266478,
    0.011529447510838509,
    -0.062316786497831345,
    0.06496089696884155,
    0.03002377413213253,
    0.05742480605840683,
    -0.0600329264998436,
    -0.04447083920240402,
    -0.03131726756691933,
    -0.05497226491570473,
    -0.005776777397841215,
    -0.013847241178154945,
    -0.04138380289077759,
    -0.0008325821836479008,
    -0.0451587475836277,
    0.005622809752821922,
    0.19324322044849396,
    -0.046559110283851624,
    0.10700493305921555,
    0.05144208297133446,
    -0.15347379446029663,
    0.00001927535231516231,
    0.049106255173683167,
    -0.023873230442404747,
    -0.01749209128320217,
    -0.0035027044359594584,
    0.04747501015663147,
    0.003928212448954582,
    0.015342849306762218,
    -0.0013528052950277925,
    0.0405891090631485,
    -0.029597042128443718,
    -4.431484765563418e-33,
    -0.021984750404953957,
    0.05619528517127037,
    -0.03994908183813095,
    0.02510102279484272,
    0.004067990928888321,
    -0.054667554795742035,
    0.03282943740487099,
    0.14705897867679596,
    0.03173254430294037,
    0.0008080806001089513,
    0.05749941244721413,
    -0.022014079615473747,
    -0.060325805097818375,
    0.011529281735420227,
    -0.07624825090169907,
    -0.018822506070137024,
    0.01693684607744217,
    -0.04259159043431282,
    -0.12817811965942383,
    0.016217688098549843,
    0.026879942044615746,
    -0.015969829633831978,
    -0.010728118009865284,
    -0.02774830348789692,
    -0.038547731935977936,
    0.08170341700315475,
    0.03231005743145943,
    -0.06969310343265533,
    -0.038799021393060684,
    0.053875863552093506,
    -0.003974419552832842,
    -0.06160392984747887,
    -0.08024194836616516,
    -0.01624215580523014,
    -0.0008304733200930059,
    0.027164874598383904,
    0.022757023572921753,
    -0.05591115728020668,
    -0.030567286536097527,
    0.12016892433166504,
    -0.02034941129386425,
    0.08228780329227448,
    -0.04375288635492325,
    -0.03394073247909546,
    0.006494170520454645,
    -0.06681056320667267,
    -0.028886334970593452,
    0.005304914433509111,
    -0.033114269375801086,
    -0.08582668751478195,
    0.010077303275465965,
    0.02270558290183544,
    0.0314047746360302,
    -0.025972524657845497,
    0.09497150033712387,
    -0.019632888957858086,
    -0.02870127186179161,
    -0.014731979928910732,
    0.049290020018815994,
    0.06537286937236786,
    0.07848556339740753,
    -0.053788043558597565,
    -0.030840422958135605,
    -0.02239474467933178,
    -0.05903873220086098,
    0.01598375290632248,
    0.04885014891624451,
    0.020002614706754684,
    -0.01947883702814579,
    0.0597991906106472,
    0.06500210613012314,
    -0.029790548607707024,
    0.018387621268630028,
    -0.036567214876413345,
    -0.13288280367851257,
    0.04652762785553932,
    -0.027057411149144173,
    0.03503134846687317,
    0.0054250298999249935,
    -0.03769238293170929,
    -0.01898871175944805,
    -0.042471930384635925,
    -0.008342130109667778,
    0.026567963883280754,
    0.009298782795667648,
    0.051262691617012024,
    0.04873053729534149,
    -0.09564484655857086,
    0.03186710923910141,
    0.013364631682634354,
    0.0051335967145860195,
    0.006361189763993025,
    0.008182411082088947,
    0.006250257603824139,
    0.04239024966955185,
    -4.44618883932435e-8,
    -0.053513359278440475,
    -0.10268884152173996,
    0.031216654926538467,
    -0.006785841658711433,
    0.03138461336493492,
    0.048835963010787964,
    -0.012125627137720585,
    0.004158096853643656,
    0.04168635606765747,
    0.021938364952802658,
    -0.00800290983170271,
    -0.023114334791898727,
    -0.02292962744832039,
    0.032273732125759125,
    0.04217123985290527,
    -0.037669721990823746,
    0.0668611228466034,
    0.034412089735269547,
    0.0115501768887043,
    0.010624479502439499,
    0.05828850343823433,
    -0.025862619280815125,
    0.011239261366426945,
    -0.03044009581208229,
    -0.04805326461791992,
    0.0006600442575290799,
    0.001679420005530119,
    -0.004220209550112486,
    0.029027221724390984,
    -0.0269871074706316,
    -0.060143567621707916,
    0.10524893552064896,
    -0.018209408968687057,
    -0.08018895983695984,
    0.013659081421792507,
    -0.029694989323616028,
    0.02379836142063141,
    -0.03329526260495186,
    -0.06484219431877136,
    -0.02957194112241268,
    -0.025295885279774666,
    0.014539052732288837,
    0.09166746586561203,
    0.05258358269929886,
    0.038204312324523926,
    -0.012992109172046185,
    0.12220301479101181,
    0.022314485162496567,
    -0.0701320543885231,
    0.035621631890535355,
    -0.05381929129362106,
    -0.01395166851580143,
    0.03498425334692001,
    0.03624434396624565,
    0.03552883490920067,
    -0.034472137689590454,
    0.018444327637553215,
    -0.10010740906000137,
    -0.08824295550584793,
    0.05593900382518768,
    0.041739609092473984,
    -0.11432301998138428,
    -0.06532149016857147,
    0.018913201987743378
  ],
  "locked_fields": [],
  "local_image_path": "C:\\Users\\atanu\\Desktop\\ULAB-DomainNetwork\\scraper\\..\\data\\images\\muhammad-aminuzzaman.jpg"
}