{
  "id": "sajid-amit",
  "name": "Sajid Amit",
  "title": "Associate Professor",
  "department": "School of Business",
  "school": "",
  "profile_url": "https://ulab.edu.bd/faculty/sajid-amit",
  "photo_url": "https://ulab.edu.bd/sites/default/files/styles/faculty_avatar/public/images/faculty/Sajid%20sir%20web.jpg?itok=_8ZU1Xkt",
  "bio_raw": "Sajid Amit has more than seventeen years of experience in four distinct sectors: investment banking, management consulting, academia, and social/market research. He was a Director at BRAC EPL Stock Brokerage Limited where at the age of twenty-nine he was the youngest Director at a BRAC company. At BRAC EPL, he managed a portfolio of US$ 250 million, mostly those of foreign institutional investors such as Morgan Stanley, Goldman Sachs, JP Morgan, and Deutsche Bank amongst others.\nHe has overseen research operations of KPMG's global offices in the US, UK, and EU. He has also won back-to-back research awards from BlackRock (UK) Advisory Ltd. Research Award and Morgan Stanley Investment Management (2012-2013). Furthermore, he is a recipient of KPMG India's Outstanding Performer of the Year Award (2009), Columbia University's prestigious Richard Hofstadter Faculty Fellowship (2007), Columbia University's South Asia Institute Research Award (2006), and Dartmouth College's Vivian B. Allen Foundation Scholarship (2000-2004). Last but not least, he was one of the twenty-five Global Leaders under twenty-one selected by Credit Suisse in New York.",
  "stated_interests": [
    "Capital Markets, Macro Economy, Social Enterprises, Mobile Financial Services, Corporate Social Responsibility"
  ],
  "education": [
    {
      "raw": "Education\nMA\n, Columbia University, New York City, NY, USA\nMA\n, SOAS, University of London, London, UK\nBA,\nDartmouth College, Hanover, New Hampshire, USA"
    }
  ],
  "publications_raw": [
    "Journal Articles\nUnderstanding social enterprises-III: Looking forward to a promising future\nhttp://www.thefinancialexpress-bd.com/2016/08/14/42063/Looking-forward-to-a-promising-future?\nUnderstanding social enterprises-II: Supportive policy environment is a critical prop\nhttp://www.thefinancialexpress-bd.com/2016/08/13/41975/Supportive-policy-environment-is-a-critical-prop\nUnderstanding social enterprises-I: A business model that witnesses a wide embrace\nhttp://print.thefinancialexpress-bd.com/2016/08/13/148974\nWhy should companies do good?\nhttp://archive.dhakatribune.com/business/2016/jun/26/why-should-companies-do-good\nThe importance of multidisciplinary education\nhttp://archive.dhakatribune.com/business/2016/jun/19/importance-multi-disciplinary-education\nReading in a time of dubsmash\nhttp://archive.dhakatribune.com/business/2016/jul/11/reading-time-dubsmash\nThe story of the $100 Bill\nhttp://archive.dhakatribune.com/begin-day/2016/jun/13/story-100-bill\nThe budget and outlook for banks, capital markets and NBFIs\nhttp://archive.dhakatribune.com/bangladesh/2016/jun/11/budget-and-outlook-banks-capital-markets-and-nbfis\nA budget for middle-income aspirations\nhttp://archive.dhakatribune.com/op-ed/2016/jun/02/budget-middle-income-aspirations"
  ],
  "extracted_keywords": [
    {
      "term": "social enterprises",
      "canonical": "Social Enterprises",
      "weight": 0.8,
      "source": "bio+pubs",
      "verified": false
    },
    {
      "term": "multidisciplinary education",
      "canonical": "Multidisciplinary Education",
      "weight": 0.5,
      "source": "pubs",
      "verified": false
    },
    {
      "term": "capital markets",
      "canonical": "Capital Market Development",
      "weight": 0.6,
      "source": "bio+interests",
      "verified": false
    },
    {
      "term": "macro economy",
      "canonical": "Macro Economy",
      "weight": 0.5,
      "source": "bio+interests",
      "verified": false
    },
    {
      "term": "corporate social responsibility",
      "canonical": "Corporate Social Responsibility",
      "weight": 0.4,
      "source": "bio+interests",
      "verified": false
    },
    {
      "term": "mobile financial services",
      "canonical": "Mobile Financial Services",
      "weight": 0.3,
      "source": "bio+interests",
      "verified": false
    }
  ],
  "embedding": [
    -0.025412095710635185,
    -0.06260211020708084,
    -0.08541813492774963,
    -0.006890036165714264,
    0.0590946227312088,
    0.08038757741451263,
    0.02047201432287693,
    0.06984350830316544,
    0.014169324189424515,
    -0.00312805431894958,
    -0.023188309744000435,
    -0.017802614718675613,
    0.004423575475811958,
    0.014102956280112267,
    0.007964839227497578,
    -0.017106804996728897,
    -0.009477847255766392,
    -0.0021325580310076475,
    -0.03831305354833603,
    -0.09640498459339142,
    -0.07294410467147827,
    -0.01743532344698906,
    0.049984727054834366,
    -0.017489561811089516,
    0.08189494162797928,
    -0.0641060546040535,
    0.03379301726818085,
    -0.040747642517089844,
    -0.04705845192074776,
    0.02681789919734001,
    0.10071460157632828,
    0.049488700926303864,
    -0.005845107603818178,
    -0.0014470370952039957,
    -0.007405121345072985,
    0.07143983989953995,
    -0.0012685656547546387,
    0.033543314784765244,
    0.001854431931860745,
    -0.0956730991601944,
    0.013778184540569782,
    -0.0033016072120517492,
    -0.03347749263048172,
    -0.07252005487680435,
    0.06345444917678833,
    -0.08762267976999283,
    0.006927833892405033,
    -0.06354588270187378,
    -0.07318378239870071,
    -0.01657731644809246,
    -0.09791291505098343,
    -0.04949060454964638,
    0.01052361261099577,
    -0.08092417567968369,
    -0.04671855270862579,
    0.03752806410193443,
    -0.02129460871219635,
    -0.022128179669380188,
    0.05298033356666565,
    -0.055608030408620834,
    -0.008198589086532593,
    -0.06189553067088127,
    0.02479405514895916,
    0.03889806568622589,
    0.00025369838112965226,
    0.002227295655757189,
    -0.010575659573078156,
    0.05593569949269295,
    -0.01949460059404373,
    -0.014580459333956242,
    0.11025205999612808,
    -0.11519116163253784,
    -0.05676759406924248,
    -0.0004680329002439976,
    0.009758788160979748,
    0.013465791940689087,
    0.03553276136517525,
    0.05917295068502426,
    0.05477900430560112,
    -0.03179646283388138,
    0.05256236344575882,
    0.03180414065718651,
    0.06954846531152725,
    -0.01776968315243721,
    -0.06659012287855148,
    -0.04193085432052612,
    0.07066535949707031,
    0.02061542682349682,
    0.005010044667869806,
    0.06150138005614281,
    0.08522314578294754,
    0.01106318086385727,
    0.07545538991689682,
    -0.0061563472263514996,
    -0.030562320724129677,
    -0.06382786482572556,
    -0.04172315448522568,
    0.027005404233932495,
    -0.05457388982176781,
    -0.012572203762829304,
    0.014691241085529327,
    0.11593259125947952,
    -0.025533732026815414,
    0.01775326207280159,
    0.0013261801796033978,
    -0.010749517008662224,
    0.10179385542869568,
    0.03451574966311455,
    0.051099009811878204,
    0.0043292585760355,
    -0.0897463709115982,
    0.08147141337394714,
    -0.057018715888261795,
    0.024038849398493767,
    0.04043157771229744,
    -0.012112063355743885,
    -0.06761818379163742,
    0.055977802723646164,
    0.06669687479734421,
    0.018544791266322136,
    0.008806552737951279,
    0.04415566101670265,
    -0.023730074986815453,
    -0.06644453853368759,
    -0.036470796912908554,
    0.032173383980989456,
    -0.08828490972518921,
    2.4063467713866275e-33,
    -0.032706718891859055,
    0.019340625032782555,
    0.06803901493549347,
    0.0182337686419487,
    -0.09583859145641327,
    0.013369749300181866,
    0.020435938611626625,
    0.019080515950918198,
    -0.10615874826908112,
    -0.004760089796036482,
    -0.023492036387324333,
    0.04106248915195465,
    0.017844995483756065,
    0.0516531728208065,
    -0.05982023850083351,
    0.03697504103183746,
    -0.09803471714258194,
    -0.02120581455528736,
    0.014899461530148983,
    -0.03578925132751465,
    0.02495567686855793,
    -0.007703214418143034,
    0.00833749957382679,
    -0.022837331518530846,
    0.06870132684707642,
    -0.09969630092382431,
    0.07737241685390472,
    0.02449951507151127,
    0.06841083616018295,
    0.05949197709560394,
    0.016807038336992264,
    -0.00619126483798027,
    -0.10375803709030151,
    -0.0002447415317874402,
    -0.0588470995426178,
    0.012785480357706547,
    -0.06242189183831215,
    -0.03207399696111679,
    0.04881453886628151,
    0.020306937396526337,
    -0.016707824543118477,
    0.06815733015537262,
    -0.008229495957493782,
    0.0016828392399474978,
    -0.02758888714015484,
    0.05394867807626724,
    0.041828256100416183,
    0.042131196707487106,
    0.03172359988093376,
    0.0761946514248848,
    -0.0941954106092453,
    -0.009646186605095863,
    -0.021413899958133698,
    0.004680383484810591,
    0.05979655683040619,
    0.02921581268310547,
    0.006762921344488859,
    0.0006109446403570473,
    -0.0343363881111145,
    -0.03053141012787819,
    -0.008440745994448662,
    -0.05064050108194351,
    -0.1141461730003357,
    0.07879677414894104,
    -0.028725996613502502,
    0.10680834949016571,
    -0.012370234355330467,
    -0.04347716271877289,
    -0.0470958948135376,
    -0.03191949427127838,
    0.014334929175674915,
    0.015668585896492004,
    0.06089914217591286,
    -0.021514229476451874,
    -0.04275444522500038,
    -0.09308065474033356,
    -0.0031293316278606653,
    0.04558377340435982,
    0.008351471275091171,
    0.05011424049735069,
    -0.04662102460861206,
    0.047528959810733795,
    0.006414829753339291,
    -0.056016791611909866,
    0.007308063562959433,
    -0.05411593243479729,
    -0.017577702179551125,
    -0.01569286733865738,
    0.05788915231823921,
    0.024873817339539528,
    -0.020110541954636574,
    -0.12243511527776718,
    0.005782322026789188,
    0.10236427932977676,
    -0.08381256461143494,
    -2.335339198415284e-33,
    -0.027880335226655006,
    -0.03565952926874161,
    0.0796232521533966,
    0.04419022798538208,
    -0.009177391417324543,
    -0.011768307536840439,
    0.05721695348620415,
    0.05028896406292915,
    0.010119110345840454,
    -0.011632219888269901,
    0.09227154403924942,
    0.03190474584698677,
    0.05192361772060394,
    0.01714027300477028,
    -0.012606075964868069,
    0.01999911293387413,
    0.0010519956704229116,
    -0.07201351225376129,
    -0.05869453772902489,
    -0.01253161858767271,
    0.09542962163686752,
    0.006722662597894669,
    0.036193206906318665,
    0.05826656520366669,
    0.02604241669178009,
    0.10330639779567719,
    0.01059083640575409,
    -0.05773473158478737,
    -0.042016465216875076,
    0.005707330536097288,
    0.03316102921962738,
    0.04935131222009659,
    -0.10386966913938522,
    0.05704517289996147,
    -0.10700225830078125,
    -0.05363401025533676,
    0.01835513673722744,
    -0.03809656575322151,
    -0.07042467594146729,
    -0.02305898629128933,
    -0.013968663290143013,
    0.04553694278001785,
    0.0012282459065318108,
    0.006908681709319353,
    0.051534973084926605,
    0.014974430203437805,
    0.0014755267184227705,
    0.02083011344075203,
    0.08458653092384338,
    -0.07482507079839706,
    -0.09970786422491074,
    0.0605367086827755,
    0.013396404683589935,
    0.029960010200738907,
    0.018434274941682816,
    0.0069570038467645645,
    0.0727374255657196,
    -0.009695461951196194,
    0.006504523102194071,
    -0.01966962032020092,
    0.06301535665988922,
    0.056620657444000244,
    0.08705347031354904,
    0.04361017420887947,
    -0.017762351781129837,
    -0.04063738137483597,
    0.03879004344344139,
    0.02041417360305786,
    -0.028492653742432594,
    -0.126958966255188,
    0.014494458213448524,
    -0.027405524626374245,
    0.0015823178691789508,
    -0.07730747759342194,
    -0.06684558093547821,
    0.08397592604160309,
    -0.06718963384628296,
    -0.0548151470720768,
    -0.05091337114572525,
    -0.019799496978521347,
    0.03599032387137413,
    0.003048182465136051,
    -0.028334109112620354,
    0.04837476834654808,
    -0.012307539582252502,
    -0.009870425797998905,
    0.05951599031686783,
    -0.0783047303557396,
    0.055270519107580185,
    -0.026835937052965164,
    -0.03963209316134453,
    -0.044403042644262314,
    0.057133451104164124,
    0.0377398356795311,
    0.09255272150039673,
    -5.446224449201509e-8,
    -0.0116887791082263,
    -0.05695255845785141,
    -0.030222170054912567,
    -0.02233584225177765,
    -0.022444890812039375,
    -0.013838769868016243,
    -0.09820431470870972,
    -0.03441281244158745,
    0.03979421779513359,
    0.04405280947685242,
    0.030930962413549423,
    -0.00838584266602993,
    -0.09918901324272156,
    0.05881746485829353,
    -0.058222364634275436,
    -0.12752309441566467,
    0.009756696410477161,
    -0.009568141773343086,
    0.04015527665615082,
    -0.012184085324406624,
    0.07393551617860794,
    0.026191845536231995,
    0.06376509368419647,
    0.004516055341809988,
    0.049225371330976486,
    -0.01079576276242733,
    -0.023509088903665543,
    0.03623957931995392,
    0.048002228140830994,
    -0.018819276243448257,
    -0.06425581127405167,
    -0.00895533338189125,
    0.06681764870882034,
    0.027834268286824226,
    0.05993431806564331,
    0.013602408580482006,
    0.058222826570272446,
    0.022375477477908134,
    -0.011752498336136341,
    0.07074586302042007,
    -0.0362611822783947,
    -0.07986530661582947,
    0.018638581037521362,
    -0.011311851441860199,
    -0.01139905583113432,
    0.027456844225525856,
    -0.02226383052766323,
    0.05867631360888481,
    0.04447208344936371,
    -0.0713530108332634,
    -0.021870017051696777,
    -0.09170430153608322,
    0.0037829065695405006,
    0.0001964830153156072,
    0.012290898710489273,
    0.064654141664505,
    -0.05165916681289673,
    -0.04457542672753334,
    -0.0097081009298563,
    0.017504345625638962,
    0.07386939972639084,
    -0.1598023623228073,
    -0.12280509620904922,
    0.04592786729335785
  ],
  "locked_fields": [],
  "local_image_path": "C:\\Users\\atanu\\Desktop\\ULAB-DomainNetwork\\scraper\\..\\data\\images\\sajid-amit.jpg",
  "keyword_extractions": {
    "legacy": {
      "keywords": [
        {
          "term": "Social Enterprises",
          "canonical": "Social Enterprising",
          "weight": 0.8,
          "source": "bio+pubs",
          "verified": true
        },
        {
          "term": "Capital Markets",
          "canonical": "Cap Mkt",
          "weight": 0.7,
          "source": "bio+pubs",
          "verified": true
        },
        {
          "term": "Macro Economy",
          "canonical": "Macroecon",
          "weight": 0.6,
          "source": "bio+pubs",
          "verified": true
        },
        {
          "term": "Corporate Social Responsibility",
          "canonical": "CSR",
          "weight": 0.5,
          "source": "bio+pubs",
          "verified": true
        },
        {
          "term": "Mobile Financial Services",
          "canonical": "MFS",
          "weight": 0.4,
          "source": "bio+pubs",
          "verified": true
        },
        {
          "term": "Original Research",
          "canonical": "OR",
          "weight": 0.3,
          "source": "pubs",
          "verified": false
        },
        {
          "term": "Economic Outlook",
          "canonical": "EO",
          "weight": 0.2,
          "source": "pubs",
          "verified": false
        },
        {
          "term": "Financial Literacy",
          "canonical": "FL",
          "weight": 0.1,
          "source": "pubs",
          "verified": false
        },
        {
          "term": "Social Entrepreneurship",
          "canonical": "SE",
          "weight": 0.9,
          "source": "bio+pubs",
          "verified": true
        },
        {
          "term": "Multidisciplinary Education",
          "canonical": "MDE",
          "weight": 0.8,
          "source": "pubs",
          "verified": false
        }
      ],
      "extracted_at": null
    },
    "llama3:8b": {
      "keywords": [
        {
          "term": "social enterprises",
          "canonical": "Social Enterprises",
          "weight": 0.8,
          "source": "bio+pubs",
          "verified": false
        },
        {
          "term": "multidisciplinary education",
          "canonical": "Multidisciplinary Education",
          "weight": 0.5,
          "source": "pubs",
          "verified": false
        },
        {
          "term": "capital markets",
          "canonical": "Capital Markets",
          "weight": 0.6,
          "source": "bio+interests",
          "verified": false
        },
        {
          "term": "macro economy",
          "canonical": "Macro Economy",
          "weight": 0.5,
          "source": "bio+interests",
          "verified": false
        },
        {
          "term": "corporate social responsibility",
          "canonical": "Corporate Social Responsibility",
          "weight": 0.4,
          "source": "bio+interests",
          "verified": false
        },
        {
          "term": "mobile financial services",
          "canonical": "Mobile Financial Services",
          "weight": 0.3,
          "source": "bio+interests",
          "verified": false
        }
      ],
      "extracted_at": "2026-07-14T04:03:02.092343+00:00"
    }
  },
  "active_extraction_model": "llama3:8b"
}